pyucc/__init__.py
pyucc/cli.py
pyucc/colors.py
pyucc/console.py
pyucc/errors.py
pyucc/symbols.py
pyucc-1.7.dist-info/LICENSE
pyucc-1.7.dist-info/METADATA
pyucc-1.7.dist-info/WHEEL
pyucc-1.7.dist-info/entry_points.txt
pyucc-1.7.dist-info/top_level.txt
pyucc-1.7.dist-info/RECORD
