Metadata-Version: 2.1
Name: pyucc
Version: 1.7
Summary: A high level, unoptimized, colored console written in python.
Home-page: https://github.com/treltasev/pyucc
Author: Trelta
Author-email: treltasev@gmail.com
Classifier: Development Status :: 4 - Beta
Classifier: Intended Audience :: Developers
Classifier: License :: OSI Approved :: MIT License
Classifier: Programming Language :: Python :: 3
Classifier: Programming Language :: Python :: 3.7
Classifier: Programming Language :: Python :: 3.8
Classifier: Programming Language :: Python :: 3.9
Classifier: Programming Language :: Python :: 3.10
License-File: LICENSE
